odoo/addons/ir_ui_view_multi_company/README.rst
odoo/addons/ir_ui_view_multi_company/__init__.py
odoo/addons/ir_ui_view_multi_company/__manifest__.py
odoo/addons/ir_ui_view_multi_company/i18n/ir_ui_view_multi_company.pot
odoo/addons/ir_ui_view_multi_company/i18n/it.po
odoo/addons/ir_ui_view_multi_company/models/__init__.py
odoo/addons/ir_ui_view_multi_company/models/base.py
odoo/addons/ir_ui_view_multi_company/models/ir_ui_view.py
odoo/addons/ir_ui_view_multi_company/readme/CONFIGURE.md
odoo/addons/ir_ui_view_multi_company/readme/CONTEXT.md
odoo/addons/ir_ui_view_multi_company/readme/CONTRIBUTORS.md
odoo/addons/ir_ui_view_multi_company/readme/DESCRIPTION.md
odoo/addons/ir_ui_view_multi_company/static/description/icon.png
odoo/addons/ir_ui_view_multi_company/static/description/index.html
odoo/addons/ir_ui_view_multi_company/tests/__init__.py
odoo/addons/ir_ui_view_multi_company/tests/test_ir_ui_view_multi_company.py
odoo/addons/ir_ui_view_multi_company/views/ir_ui_view.xml
odoo_addon_ir_ui_view_multi_company-18.0.1.0.0.3.dist-info/METADATA
odoo_addon_ir_ui_view_multi_company-18.0.1.0.0.3.dist-info/WHEEL
odoo_addon_ir_ui_view_multi_company-18.0.1.0.0.3.dist-info/top_level.txt
odoo_addon_ir_ui_view_multi_company-18.0.1.0.0.3.dist-info/RECORD
